{
  "active": [
    {
      "slug": "composicao-servicos-produtos-tasks-playbooks",
      "path": "plans/composicao-servicos-produtos-tasks-playbooks.md",
      "title": "Composição Serviços/Produtos — Task → Playbook → Service",
      "summary": "Definir e implementar o modelo de composição: **Task** (menor unidade, com métrica de consumo temporal ou valor), **Playbook** (conjunto de tasks, com métrica de consumo), **Service** (conjunto de playbooks). As duas primeiras unidades (Task e Playbook) devem ter métrica de consumo — temporal ou valor.",
      "linkedAt": "2026-02-06T19:05:27.370Z",
      "status": "active"
    }
  ],
  "completed": [],
  "primary": "composicao-servicos-produtos-tasks-playbooks"
}